cellpop/__init__.py
cellpop/static/widget.css
cellpop/static/widget.js
cellpop-0.1.1.dist-info/METADATA
cellpop-0.1.1.dist-info/WHEEL
cellpop-0.1.1.dist-info/RECORD
