Metadata-Version: 2.4
Name: cellpop
Version: 0.1.1
Requires-Dist: anndata
Requires-Dist: anywidget
Requires-Dist: pandas
Provides-Extra: dev
Requires-Dist: jupyterlab; extra == 'dev'
Requires-Dist: watchfiles; extra == 'dev'
